fshafas/__init__.py
fshafas/hafas_client.py
fshafas/util.py
fshafas/fable_modules/fable_library/__init__.py
fshafas/fable_modules/fable_library/array.py
fshafas/fable_modules/fable_library/async_.py
fshafas/fable_modules/fable_library/async_builder.py
fshafas/fable_modules/fable_library/big_int.py
fshafas/fable_modules/fable_library/bit_converter.py
fshafas/fable_modules/fable_library/boolean.py
fshafas/fable_modules/fable_library/char.py
fshafas/fable_modules/fable_library/choice.py
fshafas/fable_modules/fable_library/date.py
fshafas/fable_modules/fable_library/date_offset.py
fshafas/fable_modules/fable_library/decimal.py
fshafas/fable_modules/fable_library/diagnostics.py
fshafas/fable_modules/fable_library/double.py
fshafas/fable_modules/fable_library/encoding.py
fshafas/fable_modules/fable_library/event.py
fshafas/fable_modules/fable_library/fsharp_collections.py
fshafas/fable_modules/fable_library/fsharp_core.py
fshafas/fable_modules/fable_library/global_.py
fshafas/fable_modules/fable_library/guid.py
fshafas/fable_modules/fable_library/int32.py
fshafas/fable_modules/fable_library/list.py
fshafas/fable_modules/fable_library/long.py
fshafas/fable_modules/fable_library/mailbox_processor.py
fshafas/fable_modules/fable_library/map.py
fshafas/fable_modules/fable_library/map_util.py
fshafas/fable_modules/fable_library/mutable_map.py
fshafas/fable_modules/fable_library/mutable_set.py
fshafas/fable_modules/fable_library/native.py
fshafas/fable_modules/fable_library/numeric.py
fshafas/fable_modules/fable_library/observable.py
fshafas/fable_modules/fable_library/option.py
fshafas/fable_modules/fable_library/range.py
fshafas/fable_modules/fable_library/reflection.py
fshafas/fable_modules/fable_library/reg_exp.py
fshafas/fable_modules/fable_library/resize_array.py
fshafas/fable_modules/fable_library/seq.py
fshafas/fable_modules/fable_library/seq2.py
fshafas/fable_modules/fable_library/set.py
fshafas/fable_modules/fable_library/string.py
fshafas-0.0.13.dist-info/METADATA
fshafas-0.0.13.dist-info/WHEEL
fshafas-0.0.13.dist-info/top_level.txt
fshafas-0.0.13.dist-info/RECORD
