Metadata-Version: 2.1
Name: fshafas
Version: 0.0.13
Summary: python client for HAFAS public transport APIs
Home-page: https://github.com/bergmannjg/fshafas
Author: Jürgen Bergmann
Author-email: jbergmann@posteo.de
License: MIT
Classifier: Development Status :: 3 - Alpha
Classifier: Intended Audience :: Developers
Classifier: Programming Language :: Python :: 3.8
Requires-Python: >=3.8
Requires-Dist: requests
Requires-Dist: python-slugify
Requires-Dist: polyline
Requires-Dist: jsonpickle
